MANIFEST.in
README.md
requirements.txt
setup.py
version.txt
madeout/__init__.py
madeout/tests.py
madeout.egg-info/PKG-INFO
madeout.egg-info/SOURCES.txt
madeout.egg-info/dependency_links.txt
madeout.egg-info/not-zip-safe
madeout.egg-info/requires.txt
madeout.egg-info/top_level.txt