Metadata-Version: 1.0
Name: madeout
Version: 0.0.1
Summary: madeout.info
Home-page: http://pypi.python.org/pypi/madeout/
Author: Andre Farzat
Author-email: andrefarzat@gmail.com
License: LICENSE
Platform: UNKNOWN
